metricdb/__init__.py
metricdb/api/__init__.py
metricdb/api/api.py
metricdb/api/model.py
metricdb/api/entry/http.py
metricdb/api/entry/ws.py
metricdb/api/info/http.py
metricdb/api/info/ws.py
metricdb/client/__init__.py
metricdb/client/_client.py
metricdb/client/client.py
metricdb/client/local.py
metricdb/client/model.py
metricdb/client/remote.py
metricdb/core/__init__.py
metricdb/core/identifier.py
metricdb/core/metric.py
metricdb/core/metricdb.py
metricdb/core/time.py
metricdb/core/typing.py
metricdb/server/__main__.py
tshrag_metricdb-0.1.0.dist-info/licenses/LICENSE
tshrag_metricdb-0.1.0.dist-info/METADATA
tshrag_metricdb-0.1.0.dist-info/WHEEL
tshrag_metricdb-0.1.0.dist-info/top_level.txt
tshrag_metricdb-0.1.0.dist-info/RECORD
