Metadata-Version: 2.4
Name: Tshrag-MetricDB
Version: 0.1.0
Summary: MetricDB is a database for storing and querying time based metrics data.
Home-page: https://github.com/Tarcadia/MetricDB
Author: Tarcadia
Author-email: dont@email.me
License: MIT
Project-URL: Bug Reports, https://github.com/Tarcadia/MetricDB/issues
Project-URL: Source, https://github.com/Tarcadia/MetricDB
Keywords: MetricDB,metrics,database,Tarcadia
Classifier: Development Status :: 2 - Pre-Alpha
Classifier: Environment :: Console
Classifier: Intended Audience :: Developers
Classifier: Programming Language :: Python :: 3.11
Classifier: Operating System :: OS Independent
Classifier: Typing :: Typed
Requires-Python: >=3.11, <4
License-File: LICENSE
Requires-Dist: pydantic
Requires-Dist: tzlocal
Requires-Dist: httpx
Requires-Dist: websockets
Requires-Dist: pydantic
Requires-Dist: uvicorn
Requires-Dist: fastapi
Requires-Dist: click
Dynamic: author
Dynamic: author-email
Dynamic: classifier
Dynamic: description
Dynamic: description-content-type
Dynamic: home-page
Dynamic: keywords
Dynamic: license
Dynamic: license-file
Dynamic: project-url
Dynamic: requires-dist
Dynamic: requires-python
Dynamic: summary
